gpt_researcher_mcp/__init__.py
gpt_researcher_mcp/server.py
gpt_researcher_mcp-0.1.5.dist-info/METADATA
gpt_researcher_mcp-0.1.5.dist-info/WHEEL
gpt_researcher_mcp-0.1.5.dist-info/entry_points.txt
gpt_researcher_mcp-0.1.5.dist-info/licenses/LICENSE
gpt_researcher_mcp-0.1.5.dist-info/RECORD
