Metadata-Version: 2.4
Name: gpt-researcher-mcp
Version: 0.1.5
Summary: A MCP server project
Project-URL: Homepage, https://github.com/markchiang/gpt-researcher-mcp
Project-URL: Bug Tracker, https://github.com/markchiang/gpt-researcher-mcp/issues
Author-email: Mark Chiang <markchiang@gmail.com>
License: MIT
License-File: LICENSE
Requires-Python: >=3.11
Requires-Dist: asyncio>=3.4.3
Requires-Dist: gpt-researcher>=0.12.19
Requires-Dist: langchain-google-genai>=2.1.2
Requires-Dist: mcp[cli]>=1.6.0
